README.md
setup.py
taskDispatch/__init__.py
taskDispatch/taskdispatch.py
taskDispatch.egg-info/PKG-INFO
taskDispatch.egg-info/SOURCES.txt
taskDispatch.egg-info/dependency_links.txt
taskDispatch.egg-info/top_level.txt